Metadata-Version: 2.1
Name: votepy
Version: 0.0.1
Summary: A Python library of ordinal-based committee (OBC) voting rules
Home-page: https://github.com/Janix4000/votepy/
Author: Jan Izydorczyk, Mateusz Słuszniak, Filip Nikolow
License: MIT
Project-URL: Bug Tracker, https://github.com/Janix4000/votepy/issues
Platform: unix
Platform: linux
Platform: osx
Platform: cygwin
Platform: win32
Classifier: Programming Language :: Python :: 3
Classifier: Programming Language :: Python :: 3 :: Only
Classifier: Programming Language :: Python :: 3.7
Classifier: Programming Language :: Python :: 3.8
Classifier: Programming Language :: Python :: 3.9
Requires-Python: >=3.9
License-File: LICENSE
Requires-Dist: numpy (>=1)
Requires-Dist: matplotlib (>=3)
Requires-Dist: scipy (>=1)
Provides-Extra: testing
Requires-Dist: pytest (>=7.0) ; extra == 'testing'
Requires-Dist: pytest-cov (>=2.0) ; extra == 'testing'
Requires-Dist: mypy (>=0.971) ; extra == 'testing'
Requires-Dist: flake8 (>=3.9) ; extra == 'testing'
Requires-Dist: tox (>=3.25) ; extra == 'testing'
